cwt/__init__.py
cwt/algs/__init__.py
cwt/algs/asymmetric.py
cwt/algs/ec2.py
cwt/algs/non_aead.py
cwt/algs/okp.py
cwt/algs/raw.py
cwt/algs/rsa.py
cwt/algs/symmetric.py
cwt/cbor_processor.py
cwt/claims.py
cwt/const.py
cwt/cose.py
cwt/cose_key.py
cwt/cose_key_interface.py
cwt/cose_message.py
cwt/cwt.py
cwt/encrypted_cose_key.py
cwt/enums.py
cwt/exceptions.py
cwt/helpers/__init__.py
cwt/helpers/hcert.py
cwt/py.typed
cwt/recipient.py
cwt/recipient_algs/__init__.py
cwt/recipient_algs/aes_key_wrap.py
cwt/recipient_algs/direct.py
cwt/recipient_algs/direct_hkdf.py
cwt/recipient_algs/direct_key.py
cwt/recipient_algs/ecdh_aes_key_wrap.py
cwt/recipient_algs/ecdh_direct_hkdf.py
cwt/recipient_algs/hpke.py
cwt/recipient_interface.py
cwt/recipients.py
cwt/signer.py
cwt/utils.py
cwt-3.2.0.dist-info/METADATA
cwt-3.2.0.dist-info/WHEEL
cwt-3.2.0.dist-info/licenses/LICENSE
cwt-3.2.0.dist-info/RECORD
