Metadata-Version: 2.4
Name: cwt
Version: 3.2.0
Summary: A Python implementation of CWT/COSE.
License: MIT
License-File: LICENSE
Author: Ajitomi Daisuke
Author-email: dajiaji@gmail.com
Requires-Python: >=3.9.2,<4.0.0
Classifier: License :: OSI Approved :: MIT License
Classifier: Programming Language :: Python :: 3
Classifier: Programming Language :: Python :: 3.10
Classifier: Programming Language :: Python :: 3.11
Classifier: Programming Language :: Python :: 3.12
Classifier: Programming Language :: Python :: 3.13
Classifier: Programming Language :: Python :: 3.14
Requires-Dist: cbor2 (>=5.4.2,<6.0.0)
Requires-Dist: cryptography (>=42.0.1,<47)
Requires-Dist: pyhpke (>=0.5.3,<1.0.0)
Project-URL: Repository, https://github.com/dajiaji/python-cwt
